shrimpy/__init__.py
shrimpy/engine.py
shrimpy/main.py
shrimpy-0.1.13.dist-info/entry_points.txt
shrimpy-0.1.13.dist-info/WHEEL
shrimpy-0.1.13.dist-info/METADATA
shrimpy-0.1.13.dist-info/RECORD
