Metadata-Version: 2.1
Name: shrimpy
Version: 0.1.13
Summary: A minimal engine for choose-your-own-adventure games.
Home-page: https://github.com/yosoi/shrimpy
License: GPL-3.0-only
Author: Yosoi
Author-email: yosoi@protonmail.com
Requires-Python: >=3.6,<4.0
Classifier: License :: OSI Approved :: GNU General Public License v3 (GPLv3)
Classifier: Programming Language :: Python :: 3
Classifier: Programming Language :: Python :: 3.6
Classifier: Programming Language :: Python :: 3.7
Classifier: Programming Language :: Python :: 3.8
Classifier: Topic :: Games/Entertainment
Requires-Dist: fire (>=0.2.1,<0.3.0)
Requires-Dist: jsonschema (>=3.2.0,<4.0.0)
Project-URL: Repository, https://github.com/yosoi/shrimpy
